aiinitiate/__init__.py
aiinitiate/basic/__init__.py
aiinitiate/basic/common_utils.py
aiinitiate/cli.py
aiinitiate/config.py
aiinitiate/g.py
aiinitiate/sysinfo.py
aiinitiate/tools/__init__.py
aiinitiate/tools/builtin_tools.py
aiinitiate/tools/downloader.py
aiinitiate/tools/setter/__init__.py
aiinitiate/tools/setter/base.py
aiinitiate/tools/tool.py
aiinitiate-0.1.7.dist-info/METADATA
aiinitiate-0.1.7.dist-info/WHEEL
aiinitiate-0.1.7.dist-info/entry_points.txt
aiinitiate-0.1.7.dist-info/RECORD
